[
  {
    "question": "What is 25% of 200?",
    "options": ["40", "50", "60", "70"],
    "answer": 1,
    "explanation": "25% of 200 = (25/100) × 200 = 50"
  },
  {
    "question": "If a product costs ₹500 and profit is 20%, selling price is?",
    "options": ["₹550", "₹600", "₹650", "₹700"],
    "answer": 1,
    "explanation": "SP = 500 + 20% of 500 = 600"
  },
  {
    "question": "Average of 10, 20, 30, 40, 50?",
    "options": ["25", "30", "35", "40"],
    "answer": 1,
    "explanation": "Sum = 150, Average = 150/5 = 30"
  },
  {
    "question": "If 5 workers complete work in 10 days, 10 workers take?",
    "options": ["2 days", "5 days", "8 days", "10 days"],
    "answer": 1,
    "explanation": "Workers double, time halves."
  },
  {
    "question": "Train speed 60 km/h, distance 180 km, time taken?",
    "options": ["2 hrs", "3 hrs", "4 hrs", "5 hrs"],
    "answer": 1,
    "explanation": "Time = Distance / Speed = 180/60 = 3"
  },
  {
    "question": "Simple Interest on ₹1000 at 10% for 2 years?",
    "options": ["100", "150", "200", "250"],
    "answer": 2,
    "explanation": "SI = (P×R×T)/100 = 200"
  },
  {
    "question": "Ratio of 20:30 simplifies to?",
    "options": ["2:3", "3:2", "4:5", "5:6"],
    "answer": 0,
    "explanation": "Divide by 10."
  },
  {
    "question": "What is 15% of 300?",
    "options": ["35", "40", "45", "50"],
    "answer": 2,
    "explanation": "15% of 300 = 45"
  },
  {
    "question": "A number divisible by 2 and 5 is divisible by?",
    "options": ["10", "15", "20", "25"],
    "answer": 0,
    "explanation": "LCM of 2 and 5 = 10"
  },
  {
    "question": "If CP = ₹800 and SP = ₹720, loss %?",
    "options": ["5%", "10%", "15%", "20%"],
    "answer": 1,
    "explanation": "Loss = 80, loss% = 10%"
  },
  {
    "question": "Compound interest on ₹1000 at 10% for 2 years?",
    "options": ["200", "210", "220", "230"],
    "answer": 1,
    "explanation": "Amount = 1210, CI = 210"
  },
  {
    "question": "What is 3/4 of 200?",
    "options": ["100", "120", "150", "180"],
    "answer": 2,
    "explanation": "3/4 × 200 = 150"
  },
  {
    "question": "If 12 men do work in 8 days, 6 men take?",
    "options": ["12", "14", "16", "18"],
    "answer": 2,
    "explanation": "Half workers = double time"
  },
  {
    "question": "Speed = 40 km/h, time = 5 hrs, distance?",
    "options": ["180", "190", "200", "210"],
    "answer": 2,
    "explanation": "Distance = Speed × Time"
  },
  {
    "question": "Average of first 5 natural numbers?",
    "options": ["2", "3", "4", "5"],
    "answer": 1,
    "explanation": "1+2+3+4+5 = 15, average = 3"
  },
  {
    "question": "20% increase on 500 = ?",
    "options": ["550", "600", "650", "700"],
    "answer": 1,
    "explanation": "20% of 500 = 100"
  },
  {
    "question": "What is 50% of 90?",
    "options": ["35", "40", "45", "50"],
    "answer": 2,
    "explanation": "Half of 90 = 45"
  },
  {
    "question": "LCM of 4 and 6?",
    "options": ["10", "12", "16", "18"],
    "answer": 1,
    "explanation": "LCM = 12"
  },
  {
    "question": "HCF of 12 and 18?",
    "options": ["3", "6", "9", "12"],
    "answer": 1,
    "explanation": "HCF = 6"
  },
  {
    "question": "A train crosses 120 km in 2 hours. Speed?",
    "options": ["50", "60", "70", "80"],
    "answer": 1,
    "explanation": "120/2 = 60"
  },
  {
    "question": "Profit % if CP=100, SP=125?",
    "options": ["20%", "25%", "30%", "35%"],
    "answer": 1,
    "explanation": "Profit = 25%"
  },
  {
    "question": "1/5 of 250?",
    "options": ["40", "45", "50", "55"],
    "answer": 2,
    "explanation": "250/5 = 50"
  },
  {
    "question": "Average of 8, 12, 16?",
    "options": ["10", "12", "14", "16"],
    "answer": 1,
    "explanation": "36/3 = 12"
  },
  {
    "question": "Time if distance=100 km and speed=25 km/h?",
    "options": ["2", "3", "4", "5"],
    "answer": 2,
    "explanation": "100/25 = 4"
  },
  {
    "question": "25% of 400?",
    "options": ["80", "90", "100", "120"],
    "answer": 2,
    "explanation": "25% of 400 = 100"
  }
  ,
{
  "question": "If 8 workers complete work in 15 days, 4 workers take?",
  "options": ["20", "25", "30", "35"],
  "answer": 2,
  "explanation": "Half workers = double time = 30 days"
},
{
  "question": "What is 10% of 750?",
  "options": ["65", "70", "75", "80"],
  "answer": 2,
  "explanation": "10% of 750 = 75"
},
{
  "question": "Profit if CP=₹200 and SP=₹260?",
  "options": ["₹40", "₹50", "₹60", "₹70"],
  "answer": 2,
  "explanation": "260 - 200 = 60"
},
{
  "question": "Average of 5, 10, 15, 20?",
  "options": ["10", "12.5", "15", "17.5"],
  "answer": 1,
  "explanation": "Sum = 50, Average = 12.5"
},
{
  "question": "Distance covered at 80 km/h in 3 hours?",
  "options": ["220", "230", "240", "250"],
  "answer": 2,
  "explanation": "80 × 3 = 240"
},
{
  "question": "Simple Interest on ₹2000 at 5% for 2 years?",
  "options": ["150", "200", "250", "300"],
  "answer": 1,
  "explanation": "SI = (2000×5×2)/100 = 200"
},
{
  "question": "What is 30% of 500?",
  "options": ["100", "120", "150", "180"],
  "answer": 2,
  "explanation": "30% of 500 = 150"
},
{
  "question": "HCF of 20 and 30?",
  "options": ["5", "10", "15", "20"],
  "answer": 1,
  "explanation": "HCF = 10"
},
{
  "question": "LCM of 5 and 7?",
  "options": ["30", "35", "40", "45"],
  "answer": 1,
  "explanation": "LCM = 35"
},
{
  "question": "If SP=₹900 and profit=₹100, CP?",
  "options": ["700", "750", "800", "850"],
  "answer": 2,
  "explanation": "CP = SP - Profit"
},
{
  "question": "25% decrease of 200?",
  "options": ["140", "150", "160", "170"],
  "answer": 1,
  "explanation": "25% of 200 = 50, remaining = 150"
},
{
  "question": "If speed doubles, time becomes?",
  "options": ["Double", "Half", "Same", "Triple"],
  "answer": 1,
  "explanation": "Speed and time are inversely proportional."
},
{
  "question": "Average of 100 and 200?",
  "options": ["120", "140", "150", "160"],
  "answer": 2,
  "explanation": "(100+200)/2 = 150"
},
{
  "question": "What is 40% of 250?",
  "options": ["80", "90", "100", "110"],
  "answer": 2,
  "explanation": "40% of 250 = 100"
},
{
  "question": "1/4 of 160?",
  "options": ["30", "35", "40", "45"],
  "answer": 2,
  "explanation": "160/4 = 40"
},
{
  "question": "Train speed 90 km/h, time 2 hrs, distance?",
  "options": ["160", "170", "180", "190"],
  "answer": 2,
  "explanation": "90 × 2 = 180"
},
{
  "question": "Profit % if CP=₹400 and SP=₹500?",
  "options": ["20%", "25%", "30%", "35%"],
  "answer": 1,
  "explanation": "Profit = 100, Profit% = 25%"
},
{
  "question": "What is 5% of 1000?",
  "options": ["25", "40", "50", "60"],
  "answer": 2,
  "explanation": "5% of 1000 = 50"
},
{
  "question": "A train covers 300 km in 5 hours. Speed?",
  "options": ["50", "60", "70", "80"],
  "answer": 1,
  "explanation": "300/5 = 60"
},
{
  "question": "Compound interest on ₹1000 at 20% for 2 years?",
  "options": ["400", "420", "440", "460"],
  "answer": 2,
  "explanation": "1000 × 1.2 × 1.2 = 1440, CI = 440"
},
{
  "question": "Ratio 12:18 simplifies to?",
  "options": ["2:3", "3:2", "4:5", "6:7"],
  "answer": 0,
  "explanation": "Divide both by 6"
},
{
  "question": "Average of 2, 4, 6, 8?",
  "options": ["4", "5", "6", "7"],
  "answer": 1,
  "explanation": "20/4 = 5"
},
{
  "question": "If 3 pens cost ₹30, 1 pen costs?",
  "options": ["₹5", "₹8", "₹10", "₹12"],
  "answer": 2,
  "explanation": "30/3 = 10"
},
{
  "question": "15% of 600?",
  "options": ["80", "85", "90", "95"],
  "answer": 2,
  "explanation": "15% of 600 = 90"
},
{
  "question": "Time taken to cover 150 km at 50 km/h?",
  "options": ["2", "2.5", "3", "3.5"],
  "answer": 2,
  "explanation": "150/50 = 3"
},
{
    "question": "What is 35% of 400?",
    "options": ["120", "130", "140", "150"],
    "answer": 2,
    "explanation": "35% of 400 = 140"
  },
  {
    "question": "If CP = ₹600 and SP = ₹720, profit percentage is?",
    "options": ["15%", "20%", "25%", "30%"],
    "answer": 1,
    "explanation": "Profit = 120, Profit% = 20%"
  },
  {
    "question": "Average of 12, 18, 24, 30?",
    "options": ["18", "20", "21", "24"],
    "answer": 2,
    "explanation": "84/4 = 21"
  },
  {
    "question": "If 15 workers finish a job in 12 days, 20 workers will take?",
    "options": ["8", "9", "10", "11"],
    "answer": 1,
    "explanation": "15×12 = 20×x, x=9"
  },
  {
    "question": "Distance covered at 75 km/h in 4 hours?",
    "options": ["250", "275", "300", "325"],
    "answer": 2,
    "explanation": "75 × 4 = 300"
  },
  {
    "question": "Simple Interest on ₹3000 at 8% for 2 years?",
    "options": ["420", "450", "480", "500"],
    "answer": 2,
    "explanation": "SI = 3000×8×2/100 = 480"
  },
  {
    "question": "Ratio 18:24 simplifies to?",
    "options": ["2:3", "3:4", "4:5", "5:6"],
    "answer": 1,
    "explanation": "Divide by 6"
  },
  {
    "question": "What is 12.5% of 160?",
    "options": ["15", "20", "25", "30"],
    "answer": 1,
    "explanation": "12.5% = 1/8, 160/8 = 20"
  },
  {
    "question": "HCF of 24 and 36?",
    "options": ["6", "8", "12", "18"],
    "answer": 2,
    "explanation": "HCF = 12"
  },
  {
    "question": "LCM of 8 and 12?",
    "options": ["16", "20", "24", "32"],
    "answer": 2,
    "explanation": "LCM = 24"
  },
  {
    "question": "If SP = ₹1500 and loss = ₹300, CP is?",
    "options": ["1600", "1700", "1800", "1900"],
    "answer": 2,
    "explanation": "CP = SP + Loss"
  },
  {
    "question": "What is 60% of 250?",
    "options": ["130", "140", "150", "160"],
    "answer": 2,
    "explanation": "60% of 250 = 150"
  },
  {
    "question": "Average of first 10 natural numbers?",
    "options": ["5", "5.5", "6", "6.5"],
    "answer": 1,
    "explanation": "55/10 = 5.5"
  },
  {
    "question": "A train covers 420 km in 6 hours. Speed?",
    "options": ["60", "65", "70", "75"],
    "answer": 2,
    "explanation": "420/6 = 70"
  },
  {
    "question": "Compound Interest on ₹2000 at 10% for 2 years?",
    "options": ["400", "420", "440", "460"],
    "answer": 1,
    "explanation": "2000×1.1×1.1 = 2420, CI=420"
  },
  {
    "question": "1/8 of 240?",
    "options": ["25", "30", "35", "40"],
    "answer": 1,
    "explanation": "240/8 = 30"
  },
  {
    "question": "Profit % if CP = ₹800 and SP = ₹1000?",
    "options": ["20%", "25%", "30%", "35%"],
    "answer": 1,
    "explanation": "Profit = 200, Profit%=25%"
  },
  {
    "question": "What is 45% of 200?",
    "options": ["80", "90", "100", "110"],
    "answer": 1,
    "explanation": "45% of 200 = 90"
  },
  {
    "question": "If 24 men do a work in 15 days, 12 men take?",
    "options": ["20", "25", "30", "35"],
    "answer": 2,
    "explanation": "Half workers = double time"
  },
  {
    "question": "Average of 14, 16, 18, 20, 22?",
    "options": ["16", "17", "18", "19"],
    "answer": 2,
    "explanation": "90/5 = 18"
  },
  {
    "question": "25% of 640?",
    "options": ["140", "150", "160", "170"],
    "answer": 2,
    "explanation": "640/4 = 160"
  },
  {
    "question": "A number divisible by 3 and 4 is divisible by?",
    "options": ["7", "10", "12", "15"],
    "answer": 2,
    "explanation": "LCM = 12"
  },
  {
    "question": "Speed 90 km/h, distance 270 km, time?",
    "options": ["2", "3", "4", "5"],
    "answer": 1,
    "explanation": "270/90 = 3"
  },
  {
    "question": "Simple Interest on ₹5000 at 6% for 3 years?",
    "options": ["800", "850", "900", "950"],
    "answer": 2,
    "explanation": "SI = 900"
  },
  {
    "question": "Ratio 21:35 simplifies to?",
    "options": ["2:3", "3:5", "4:5", "5:7"],
    "answer": 1,
    "explanation": "Divide by 7"
  },
  {
    "question": "What is 75% of 320?",
    "options": ["220", "230", "240", "250"],
    "answer": 2,
    "explanation": "3/4 of 320 = 240"
  },
  {
    "question": "HCF of 28 and 42?",
    "options": ["7", "14", "21", "28"],
    "answer": 1,
    "explanation": "HCF = 14"
  },
  {
    "question": "LCM of 9 and 15?",
    "options": ["30", "45", "60", "75"],
    "answer": 1,
    "explanation": "LCM = 45"
  },
  {
    "question": "Profit if CP=₹750 and SP=₹900?",
    "options": ["100", "120", "150", "180"],
    "answer": 2,
    "explanation": "900-750 = 150"
  },
  {
    "question": "Average of 25, 35, 45?",
    "options": ["30", "35", "40", "45"],
    "answer": 1,
    "explanation": "105/3 = 35"
  },
  {
    "question": "20% of 850?",
    "options": ["160", "170", "180", "190"],
    "answer": 1,
    "explanation": "20% = 170"
  },
  {
    "question": "Distance at 55 km/h in 6 hours?",
    "options": ["300", "320", "330", "340"],
    "answer": 2,
    "explanation": "55×6 = 330"
  },
  {
    "question": "If 18 workers finish work in 10 days, 9 workers take?",
    "options": ["15", "18", "20", "22"],
    "answer": 2,
    "explanation": "Half workers = double time"
  },
  {
    "question": "Compound Interest on ₹5000 at 10% for 2 years?",
    "options": ["1000", "1050", "1100", "1150"],
    "answer": 1,
    "explanation": "CI = 1050"
  },
  {
    "question": "What is 2/5 of 500?",
    "options": ["180", "190", "200", "210"],
    "answer": 2,
    "explanation": "2/5 × 500 = 200"
  },
  {
    "question": "Profit % if CP=₹1200 and SP=₹1500?",
    "options": ["20%", "25%", "30%", "35%"],
    "answer": 1,
    "explanation": "300/1200×100 = 25%"
  },
  {
    "question": "Average of 6, 12, 18, 24, 30?",
    "options": ["16", "17", "18", "19"],
    "answer": 2,
    "explanation": "90/5 = 18"
  },
  {
    "question": "35% of 600?",
    "options": ["190", "200", "210", "220"],
    "answer": 2,
    "explanation": "35% of 600 = 210"
  },
  {
    "question": "A train covers 540 km in 9 hours. Speed?",
    "options": ["50", "55", "60", "65"],
    "answer": 2,
    "explanation": "540/9 = 60"
  },
  {
    "question": "Ratio 27:36 simplifies to?",
    "options": ["2:3", "3:4", "4:5", "5:6"],
    "answer": 1,
    "explanation": "Divide by 9"
  },
  {
    "question": "Simple Interest on ₹4000 at 5% for 4 years?",
    "options": ["700", "750", "800", "850"],
    "answer": 2,
    "explanation": "SI = 800"
  },
  {
    "question": "What is 80% of 150?",
    "options": ["100", "110", "120", "130"],
    "answer": 2,
    "explanation": "80% of 150 = 120"
  },
  {
    "question": "HCF of 32 and 48?",
    "options": ["8", "12", "16", "24"],
    "answer": 2,
    "explanation": "HCF = 16"
  },
  {
    "question": "LCM of 12 and 18?",
    "options": ["24", "30", "36", "48"],
    "answer": 2,
    "explanation": "LCM = 36"
  },
  {
    "question": "If SP=₹840 and loss=₹160, CP?",
    "options": ["900", "950", "1000", "1050"],
    "answer": 2,
    "explanation": "CP = 1000"
  },
  {
    "question": "Average of 9, 18, 27, 36?",
    "options": ["20", "22.5", "24", "25"],
    "answer": 1,
    "explanation": "90/4 = 22.5"
  },
  {
    "question": "15% of 800?",
    "options": ["100", "110", "120", "130"],
    "answer": 2,
    "explanation": "15% = 120"
  },
  {
    "question": "Distance covered at 120 km/h in 2.5 hours?",
    "options": ["250", "275", "300", "325"],
    "answer": 2,
    "explanation": "120×2.5 = 300"
  },
  {
    "question": "If 10 men complete a job in 20 days, 25 men take?",
    "options": ["6", "7", "8", "9"],
    "answer": 2,
    "explanation": "10×20 = 25×x, x=8"
  },
  {
    "question": "What is 5/8 of 320?",
    "options": ["180", "190", "200", "210"],
    "answer": 2,
    "explanation": "5×40 = 200"
  }
]
